compress_unit.sv
//verilator lint_off UNUSED
module compress_unit (
    input logic [31:0] inst,input logic  pc,  output logic next_comp16, output logic [31:0] compressed_inst_out
);
    logic [1:0] comp_opcode;
    logic [11:0] comp_load_i_type, comp_imm_stack_store,comp_imm_load_store, imm_Li, comp_i_tpye;
    logic [4:0] rs2, rs1,rd ;//change addded
    logic [19:0] imm_jump, imm_LUI, imm_LUI_addi_16_sp;
    logic [2:0] comp_func3;
    logic [4:0] comp_rs1, comp_rs2, comp_rd;
    
    logic [15:0] comp_inst;
    logic illegal;	//change added
    logic [4:0]imm_sLLI;	//change added 
    logic [7:0]imm;		//change added
    logic [11:0] comp_imm_branch, comp_addi_14_sp, imm_ANDI;
    logic [31:0] inst_load, inst_store, inst_load_stack, inst_store_stack, inst_jal , inst_j, inst_jalr,inst_jr, inst_branch_not, inst_branch_equal,inst_LI, inst_LUI, inst_r_type, inst_r_comp_type,inst_nop, inst_i_type, inst_addi_16_sp, inst_addi_14_sp, inst_SLLI, inst_sRLI, inst_sRAI, inst_ADD, inst_ANDI, inst_MV, inst_AND, inst_OR, inst_XOR, inst_SUB,inst_E_Break;	//change added

    logic [6:0] load_opcode, store_opcode, R_type_opcode, I_type_opcode, Jal_opcode, B_type_opcode, Jalr_opcode,LUI_opcode, AUIPC_opcode ;

    assign illegal =| comp_inst;//change
    assign comp_opcode = comp_inst [1:0];
    assign comp_load_i_type = (({{6'b0},{comp_inst[3:2]},{comp_inst[12]}, {comp_inst[6:4]}}) << 2); //for i type instruction 
    assign comp_imm_stack_store = (({{6'b0},{comp_inst[8:7]},{comp_inst[12:9]}}) << 2);  //to to store with stack register as a refernce	change
    assign imm = comp_inst[12:5];   //wide immediate
    assign comp_imm_load_store = (({{7'b0},{comp_inst[5]},{comp_inst[12:10]}, {comp_inst[6]}}) << 2); //for load and store unit   change> 7bits added
    assign comp_imm_branch = {{3{comp_inst[12]}}, {comp_inst[12]},{comp_inst[6:5]},{comp_inst[2]}, {comp_inst[11:10]}, {comp_inst[4:3]}, {1'b0}}; //for branch immediate
    assign rs2 = comp_inst [6:2];   // normal 5 bit address for rs2 
    assign rs1 = comp_inst [11:7];  // nomeal 5 bit address for rs1 and rd
    assign rd =rs1;     	    //cahnge added
    assign comp_rs1 = {{2'b01},{comp_inst[9:7]}};   // for accessing x8 -x15 registers
    assign comp_rs2 = {{2'b01},{comp_inst[4:2]}};   // for accessing x8 -x15 registers
    assign comp_rd = {{2'b01},{comp_inst[4:2]}};    // for accessing x8 -x15 registers
    assign imm_jump =  (({{8{comp_inst[12]}},{comp_inst[12]}, {comp_inst[8]},{comp_inst[10:9]} , {comp_inst[6]} , {comp_inst[7]} , {comp_inst[2]} , {comp_inst[11]} , {comp_inst[5:3]} , 1'b0 })); //immediate for jump
    assign imm_Li = {{6{comp_inst[12]}} , {comp_inst[12]} , {comp_inst[6:2]}};
    assign imm_LUI = { {2{comp_inst[12]} },{comp_inst[12]} , {comp_inst [6:2]}, {12'b0}};
    assign imm_LUI_addi_16_sp =  {{10{comp_inst[12]}} ,{comp_inst[12]}, {comp_inst [4:3]},{comp_inst[5]},{comp_inst[2]},{comp_inst[6]} ,{4'b0} } ;
    assign comp_addi_14_sp = (({{4'b0}, {comp_inst[10:7]} ,  {comp_inst[12:11]},{comp_inst[5]} , {comp_inst[6]}} ) << 4);
    assign imm_sLLI = comp_inst[6:2] ;		    // for RVC32 bit 4 of shamt shouold be zero  change 12 bit is dropped  
    assign imm_ANDI = {{6{comp_inst[12]}} , {comp_inst[12]} , {comp_inst[6:2]}};
    assign comp_i_tpye = {{6{comp_inst[12]} }  ,  {comp_inst[12]}, {comp_inst [6:2]}};
    assign comp_func3 = comp_inst[15:13];
    assign load_opcode = 7'b0000011;
    assign store_opcode =7'b0100011;
    assign R_type_opcode =7'b0110011;
    assign I_type_opcode = 7'b0010011;
    assign B_type_opcode = 7'b1100011;
    assign Jal_opcode =7'b1101111;
    assign Jalr_opcode = 7'b1100111;
    assign LUI_opcode =7'b0110111;
    assign AUIPC_opcode= 7'b0010111;


    always_comb begin // a sel that we use to isolate the compressed instruction , we read the LSD of pc bit 1 and find if we are at 0x2 or 0x4

        if(pc) comp_inst = inst[31:16];
        else comp_inst = inst[15:0];//change
        
    end

    always_comb begin // this is the sel which tells the pc to do +2 and inst_mem to to address>>1
    if (illegal) begin //check for illegal inst all zeros 					      
    case (comp_opcode)
       2'b00 : next_comp16 =1'b1;
       2'b01 : next_comp16=1'b1;
       2'b10 : next_comp16=1'b1;
       2'b11 : next_comp16 =1'b0; 
        default: next_comp16 =1'b0;
    
    endcase
    end
    
    else next_comp16= 1'b0;
    end

    always_comb begin // this is to select what output the instruction is according to the compressed opcode 
        if (~next_comp16) compressed_inst_out = inst;
        else begin 
            case (comp_opcode)
            2'b00 : begin 
                    case (comp_func3)
                    3'b000 :  compressed_inst_out = inst_addi_14_sp;
                    3'b010 :  compressed_inst_out = inst_load;
                    3'b110 :  compressed_inst_out = inst_store;
                    default compressed_inst_out = 32'h0000_0013;//change
                    endcase
                end 
            2'b01 : begin 
                    case(comp_func3)
                    3'b000 : begin 
                            if (comp_inst[11:7] == 5'b0) compressed_inst_out = 32'h0000_0013;//change
                            else compressed_inst_out = inst_i_type;
                            end
                    3'b001 : compressed_inst_out = inst_jal;
                    3'b010 : compressed_inst_out = inst_LI;
                    3'b011 : begin  if (rd == 5'h02 & rd!=5'h00)  compressed_inst_out = inst_addi_16_sp;
                                    else compressed_inst_out = inst_LUI;
                            end
                    3'b100 : begin 
                            case (comp_inst[11:10])
                            2'b00 : compressed_inst_out = inst_sRLI;
                            2'b01 : compressed_inst_out = inst_sRAI;
                            2'b10 : compressed_inst_out = inst_ANDI;
                            2'b11 : begin 
                                    case (comp_inst[6:5])
                                    2'b00 : compressed_inst_out = inst_SUB;
                                    2'b01 : compressed_inst_out = inst_XOR;
                                    2'b10 : compressed_inst_out = inst_OR;
                                    2'b11 : compressed_inst_out = inst_AND;

                                    endcase
                                    end
                            default compressed_inst_out = 32'h0000_0013;
                            endcase
                            end
                    3'b101 : compressed_inst_out = inst_j;
                    3'b110 : compressed_inst_out = inst_branch_equal;
                    3'b111 : compressed_inst_out = inst_branch_not;
                    endcase

                    end
            2'b10 : begin 
                    case (comp_func3)
                    3'b000 : compressed_inst_out = inst_SLLI;
                    3'b010 : compressed_inst_out =inst_load_stack;
                    3'b100 :  begin
                        case(comp_inst[12])
                        1'b0 : begin 
                            if((rs2 == 5'h00) & (rs1!=5'h00)) compressed_inst_out = inst_jr;
                            else compressed_inst_out = inst_MV;
                                end
                        1'b1 : begin
                            if ((rs1==5'h00) & (rs2 == 5'h00)) compressed_inst_out =inst_E_Break;
                            else if ((rs1!=5'h00) & (rs2 == 5'h00))compressed_inst_out= inst_jalr;
                            else compressed_inst_out = inst_ADD;
                        end
                        endcase
                                end 
                    3'b110 : compressed_inst_out = inst_store_stack;
                    default compressed_inst_out = 32'h0000_0013;
                    endcase
                    end
            2'b11 : compressed_inst_out = inst;
            endcase
        end


    end


    always_comb begin  // this is the block in which we make extend the compressed to whole instructions
        inst_load_stack = { {comp_load_i_type}, {5'h02} , {comp_func3} , {rs1}, {load_opcode}};     // lw rd ,offset[7:2](x2)
        inst_store_stack = {{comp_imm_stack_store[11:5]} , {rs2}, {5'h02},{3'b010}, {comp_imm_stack_store[4:0]}, {store_opcode}};   //sw rs2, offset[7:2](x2)
        inst_load = {{comp_imm_load_store}, {comp_rs1}, {comp_func3}, {comp_rd}, {load_opcode}};    // lw rd', offset[6:2](rs1')
        inst_store = {{comp_imm_load_store[11:5]}, {comp_rs2},{comp_rs1}, {3'b010}, {comp_imm_load_store[4:0]}, {store_opcode}};    //sw rs2', offset[6:2](rs1')
        inst_jal = {  {{imm_jump[19]},{imm_jump[9:0]},{imm_jump[10]},{imm_jump[18:11]}} , {5'h01}, {Jal_opcode}};  // jal x1, offset[11:1].
        inst_j = {  {{imm_jump[19]},{imm_jump[9:0]},{imm_jump[10]},{imm_jump[18:11]}} , {5'h00}, {Jal_opcode}};    //  jal x0, offset[11:1].
        inst_jr = {{12'h0} , {rs1} , {3'b0}, {5'h00}, {Jalr_opcode}};   //jalr x0, rs1, 0.
        inst_jalr= {{12'h0} , {rs1} , {3'b0}, {5'h01}, {Jalr_opcode}};  //jalr x1, rs1, 0.
        inst_branch_equal = {{{comp_imm_branch[11]} , {comp_imm_branch [9:4]}} ,{5'h00} ,  {comp_rs1} , {3'b000} , {{comp_imm_branch[3:0]},{comp_imm_branch[10]}} ,  {B_type_opcode}};  // beq rs1', x0, offset[8:1].
        inst_branch_not = {{{comp_imm_branch[11]} , {comp_imm_branch [9:4]}} ,{5'h00} ,  {comp_rs1} , {3'b001} , {{comp_imm_branch[3:0]},{comp_imm_branch[10]}} ,  {B_type_opcode}};    // bne rs1', x0, offset[8:1]
        inst_LI = {{imm_Li}, {5'h00} , {3'b0} , {rd} , {I_type_opcode}};                                // addi rd, x0, imm[5:0]
        inst_LUI = { {imm_LUI} , {rd} , {LUI_opcode}};                                                  // lui rd, nzuimm[17:12]
        inst_i_type = { {comp_i_tpye} , {rs1} , {comp_func3} , {rs1} , {I_type_opcode}}  ;              // only for  addi rd, rd, nzimm[5:0]
        inst_addi_16_sp = {{imm_LUI_addi_16_sp} , {5'h02} , {LUI_opcode}};                              // addi x2, x2, nzimm[9:4].
        inst_addi_14_sp = {{comp_addi_14_sp}, {5'h02} , {comp_func3} , {comp_rd} , {I_type_opcode}};    // addi rd', x2, nzuimm[9:2].
        inst_SLLI = {{7'b0} , {imm_sLLI} ,{rs1} , {3'b001}, {rs1}, {I_type_opcode}};                    // slli rd, rd, shamt[5:0]
        inst_sRLI = {{7'b0} , {imm_sLLI} ,{comp_rs1} , {3'b101}, {comp_rs1}, {I_type_opcode}};          // srli rd', rd', shamt[5:0]
        inst_sRAI = {{7'b0100000} , {imm_sLLI} ,{comp_rs1} , {3'b101}, {comp_rs1}, {I_type_opcode}};    // srai rd', rd', shamt[5:0]
        inst_ANDI = {{imm_ANDI} ,{comp_rs1}, {3'b111}, {comp_rs1}, {I_type_opcode}};                    // andi rd', rd', imm[5:0]
        inst_ADD = {{7'b0}, {rs2}, {rs1}, {3'b0} , {rs1} , {R_type_opcode} };                           // add rd, rd, rs2.
        inst_MV ={{7'b0}, {rs2}, {5'b0}, {3'b0} , {rs1} , {R_type_opcode} };                            // add rd, x0, rs2
        inst_AND = {{7'b0}, {comp_rs2}, {comp_rs1}, {3'b111} , {comp_rs1} , {R_type_opcode} };           // and rd', rd', rs2'
        inst_OR = {{7'b0}, {comp_rs2}, {comp_rs1}, {3'b110} , {comp_rs1} , {R_type_opcode} };            // or rd', rd', rs2'
        inst_XOR = {{7'b0}, {comp_rs2}, {comp_rs1}, {3'b100} , {comp_rs1} , {R_type_opcode} };           // xor rd', rd', rs2'
        inst_SUB = {{7'b0100000}, {comp_rs2}, {comp_rs1}, {3'b000} , {comp_rs1} , {R_type_opcode} };     // sub rd', rd', rs2'
	inst_E_Break ={{12'b000000000001},{5'b0},{3'b0},{5'b0},{7'b1110011}};
    end
endmodule

waveform.vcd
$version Generated by VerilatedVcd $end
$timescale 1ps $end

 $scope module TOP $end
  $var wire 32 Q compressed_inst_out [31:0] $end
  $var wire 32 N inst [31:0] $end
  $var wire  1 P next_comp16 $end
  $var wire  1 O pc $end
  $scope module compress_unit $end
   $var wire  7 ^ AUIPC_opcode [6:0] $end
   $var wire  7 [ B_type_opcode [6:0] $end
   $var wire  7 Y I_type_opcode [6:0] $end
   $var wire  7 Z Jal_opcode [6:0] $end
   $var wire  7 \ Jalr_opcode [6:0] $end
   $var wire  7 ] LUI_opcode [6:0] $end
   $var wire  7 X R_type_opcode [6:0] $end
   $var wire 12 4 comp_addi_14_sp [11:0] $end
   $var wire  3 - comp_func3 [2:0] $end
   $var wire 12 ' comp_i_tpye [11:0] $end
   $var wire 12 3 comp_imm_branch [11:0] $end
   $var wire 12 & comp_imm_load_store [11:0] $end
   $var wire 12 % comp_imm_stack_store [11:0] $end
   $var wire 16 0 comp_inst [15:0] $end
   $var wire 12 $ comp_load_i_type [11:0] $end
   $var wire  2 # comp_opcode [1:0] $end
   $var wire  5 / comp_rd [4:0] $end
   $var wire  5 . comp_rs1 [4:0] $end
   $var wire  5 / comp_rs2 [4:0] $end
   $var wire 32 Q compressed_inst_out [31:0] $end
   $var wire  1 1 illegal $end
   $var wire  8 2 imm [7:0] $end
   $var wire 12 ' imm_ANDI [11:0] $end
   $var wire 20 + imm_LUI [19:0] $end
   $var wire 20 , imm_LUI_addi_16_sp [19:0] $end
   $var wire 12 ' imm_Li [11:0] $end
   $var wire 20 * imm_jump [19:0] $end
   $var wire  5 ( imm_sLLI [4:0] $end
   $var wire 32 N inst [31:0] $end
   $var wire 32 G inst_ADD [31:0] $end
   $var wire 32 J inst_AND [31:0] $end
   $var wire 32 H inst_ANDI [31:0] $end
   $var wire 32 U inst_E_Break [31:0] $end
   $var wire 32 ? inst_LI [31:0] $end
   $var wire 32 @ inst_LUI [31:0] $end
   $var wire 32 I inst_MV [31:0] $end
   $var wire 32 K inst_OR [31:0] $end
   $var wire 32 D inst_SLLI [31:0] $end
   $var wire 32 M inst_SUB [31:0] $end
   $var wire 32 L inst_XOR [31:0] $end
   $var wire 32 C inst_addi_14_sp [31:0] $end
   $var wire 32 B inst_addi_16_sp [31:0] $end
   $var wire 32 > inst_branch_equal [31:0] $end
   $var wire 32 = inst_branch_not [31:0] $end
   $var wire 32 A inst_i_type [31:0] $end
   $var wire 32 : inst_j [31:0] $end
   $var wire 32 9 inst_jal [31:0] $end
   $var wire 32 ; inst_jalr [31:0] $end
   $var wire 32 < inst_jr [31:0] $end
   $var wire 32 5 inst_load [31:0] $end
   $var wire 32 7 inst_load_stack [31:0] $end
   $var wire 32 T inst_nop [31:0] $end
   $var wire 32 S inst_r_comp_type [31:0] $end
   $var wire 32 R inst_r_type [31:0] $end
   $var wire 32 F inst_sRAI [31:0] $end
   $var wire 32 E inst_sRLI [31:0] $end
   $var wire 32 6 inst_store [31:0] $end
   $var wire 32 8 inst_store_stack [31:0] $end
   $var wire  7 V load_opcode [6:0] $end
   $var wire  1 P next_comp16 $end
   $var wire  1 O pc $end
   $var wire  5 ) rd [4:0] $end
   $var wire  5 ) rs1 [4:0] $end
   $var wire  5 ( rs2 [4:0] $end
   $var wire  7 W store_opcode [6:0] $end
  $upscope $end
 $upscope $end
$enddefinitions $end


#0
b00 #
b000001110000 $
b000011100100 %
b000000100100 &
b111111110001 '
b10001 (
b00111 )
b11111111110111100000 *
b11110001000000000000 +
b11111111111000110000 ,
b011 -
b01111 .
b01001 /
b0111001111000100 0
11
b10011110 2
b111110100000 3
b011110010000 4
b00000010010001111011010010000011 5
b00000010100101111010001000100011 6
b00000111000000010011001110000011 7
b00001111000100010010001000100011 8
b10111100000111111111000011101111 9
b10111100000111111111000001101111 :
b00000000000000111000000011100111 ;
b00000000000000111000000001100111 <
b11110100000001111001000011100011 =
b11110100000001111000000011100011 >
b11111111000100000000001110010011 ?
b11110001000000000000001110110111 @
b11111111000100111011001110010011 A
b11111111111000110000000100110111 B
b01111001000000010011010010010011 C
b00000001000100111001001110010011 D
b00000001000101111101011110010011 E
b01000001000101111101011110010011 F
b00000001000100111000001110110011 G
b11111111000101111111011110010011 H
b00000001000100000000001110110011 I
b00000000100101111111011110110011 J
b00000000100101111110011110110011 K
b00000000100101111100011110110011 L
b01000000100101111000011110110011 M
b01111001011101100111001111000100 N
0O
1P
b00000000000000000000000000010011 Q
b01111101011011111111001110110111 R
b11111100110001000111000101010011 S
b01101111100111100001011100100001 T
b00000000000100000000000001110011 U
b0000011 V
b0100011 W
b0110011 X
b0010011 Y
b1101111 Z
b1100011 [
b1100111 \
b0110111 ]
b0010111 ^
#1
b000000010000 $
b000000000000 %
b000000000100 &
b000000010000 '
b10000 (
b00000 )
b00000000000010000000 *
b00010000000000000000 +
b00000000000000010000 ,
b000 -
b01000 .
b01000 /
b0000000001000000 0
b00000010 2
b000010000000 3
b000000010000 4
b00000000010001000000010000000011 5
b00000000100001000010001000100011 6
b00000001000000010000000000000011 7
b00000001000000010010000000100011 8
b00010000000000000000000011101111 9
b00010000000000000000000001101111 :
b00000000000000000000000011100111 ;
b00000000000000000000000001100111 <
b00010000000001000001000001100011 =
b00010000000001000000000001100011 >
b00000001000000000000000000010011 ?
b00010000000000000000000000110111 @
b00000001000000000000000000010011 A
b00000000000000010000000100110111 B
b00000001000000010000010000010011 C
b00000001000000000001000000010011 D
b00000001000001000101010000010011 E
b01000001000001000101010000010011 F
b00000001000000000000000000110011 G
b00000001000001000111010000010011 H
b00000001000000000000000000110011 I
b00000000100001000111010000110011 J
b00000000100001000110010000110011 K
b00000000100001000100010000110011 L
b01000000100001000000010000110011 M
b00000000010000000000000001101111 N
1O
b00000001000000010000010000010011 Q
#2
b11 #
b000011011000 $
b000001000100 &
b000000011011 '
b11011 (
b00000000000010101010 *
b00011011000000000000 +
b00000000000011110000 ,
b01011 /
b0000000001101111 0
b00000011 2
b000011100010 3
b000000110000 4
b00000100010001000000010110000011 5
b00000100101101000010001000100011 6
b00001101100000010000000000000011 7
b00000001101100010010000000100011 8
b00010101010000000000000011101111 9
b00010101010000000000000001101111 :
b00011100000001000001001001100011 =
b00011100000001000000001001100011 >
b00000001101100000000000000010011 ?
b00011011000000000000000000110111 @
b00000001101100000000000000010011 A
b00000000000011110000000100110111 B
b00000011000000010000010110010011 C
b00000001101100000001000000010011 D
b00000001101101000101010000010011 E
b01000001101101000101010000010011 F
b00000001101100000000000000110011 G
b00000001101101000111010000010011 H
b00000001101100000000000000110011 I
b00000000101101000111010000110011 J
b00000000101101000110010000110011 K
b00000000101101000100010000110011 L
b01000000101101000000010000110011 M
0O
0P
b00000000010000000000000001101111 Q
#3
b00 #
b000001000000 $
b000010000000 %
b000000000000 &
b000000000001 '
b00001 (
b00010 )
b00000000010000100000 *
b00000001000000000000 +
b00000000000000100000 ,
b110 -
b01010 .
b01001 /
b1100000100000100 0
b00001000 2
b000000100000 3
b001000000000 4
b00000000000001010110010010000011 5
b00000000100101010010000000100011 6
b00000100000000010110000100000011 7
b00001000000100010010000000100011 8
b00000100000100000000000011101111 9
b00000100000100000000000001101111 :
b00000000000000010000000011100111 ;
b00000000000000010000000001100111 <
b00000100000001010001000001100011 =
b00000100000001010000000001100011 >
b00000000000100000000000100010011 ?
b00000001000000000000000100110111 @
b00000000000100010110000100010011 A
b00000000000000100000000100110111 B
b00100000000000010110010010010011 C
b00000000000100010001000100010011 D
b00000000000101010101010100010011 E
b01000000000101010101010100010011 F
b00000000000100010000000100110011 G
b00000000000101010111010100010011 H
b00000000000100000000000100110011 I
b00000000100101010111010100110011 J
b00000000100101010110010100110011 K
b00000000100101010100010100110011 L
b01000000100101010000010100110011 M
b01000001000001001100000100000100 N
1P
b00000000100101010010000000100011 Q
#4
b010 -
b0100000100000100 0
b00000000000001010010010010000011 5
b00000100000000010010000100000011 7
b00000000000100010010000100010011 A
b00100000000000010010010010010011 C
1O
b00000000000001010010010010000011 Q
#5
b01 #
b000000000000 $
b000000000000 %
b000000000000 '
b00000 (
b00000 )
b00000000000000000000 *
b00000000000000000000 +
b00000000000000000000 ,
b000 -
b01000 .
b01000 /
b0000000000000001 0
b00000000 2
b000000000000 3
b000000000000 4
b00000000000001000000010000000011 5
b00000000100001000010000000100011 6
b00000000000000010000000000000011 7
b00000000000000010010000000100011 8
b00000000000000000000000011101111 9
b00000000000000000000000001101111 :
b00000000000000000000000011100111 ;
b00000000000000000000000001100111 <
b00000000000001000001000001100011 =
b00000000000001000000000001100011 >
b00000000000000000000000000010011 ?
b00000000000000000000000000110111 @
b00000000000000000000000000010011 A
b00000000000000000000000100110111 B
b00000000000000010000010000010011 C
b00000000000000000001000000010011 D
b00000000000001000101010000010011 E
b01000000000001000101010000010011 F
b00000000000000000000000000110011 G
b00000000000001000111010000010011 H
b00000000000000000000000000110011 I
b00000000100001000111010000110011 J
b00000000100001000110010000110011 K
b00000000100001000100010000110011 L
b01000000100001000000010000110011 M
b00000000100010010000000000000001 N
0O
b00000000000000000000000000010011 Q
#6
b000010000000 $
b000001000000 %
b000000000010 '
b00010 (
b00001 )
b00000000000001000010 *
b00000010000000000000 +
b00000000000010000000 ,
b01001 .
b01010 /
b0000000010001001 0
b00000100 2
b000000000010 3
b000100000000 4
b00000000000001001000010100000011 5
b00000000101001001010000000100011 6
b00001000000000010000000010000011 7
b00000100001000010010000000100011 8
b00001000010000000000000011101111 9
b00001000010000000000000001101111 :
b00000000000000001000000011100111 ;
b00000000000000001000000001100111 <
b00000000000001001001001001100011 =
b00000000000001001000001001100011 >
b00000000001000000000000010010011 ?
b00000010000000000000000010110111 @
b00000000001000001000000010010011 A
b00000000000010000000000100110111 B
b00010000000000010000010100010011 C
b00000000001000001001000010010011 D
b00000000001001001101010010010011 E
b01000000001001001101010010010011 F
b00000000001000001000000010110011 G
b00000000001001001111010010010011 H
b00000000001000000000000010110011 I
b00000000101001001111010010110011 J
b00000000101001001110010010110011 K
b00000000101001001100010010110011 L
b01000000101001001000010010110011 M
1O
b00000000001000001000000010010011 Q
#7
b000000001000 $
b000000010000 %
b000001010000 &
b000000001000 '
b01000 (
b10000 )
b00000000000000011000 *
b00001000000000000000 +
b00000000000001000000 ,
b001 -
b01000 .
b01000 /
b0010100000100001 0
b01000001 2
b000001010000 3
b000001100000 4
b00000101000001000001010000000011 5
b00000100100001000010100000100011 6
b00000000100000010001100000000011 7
b00000000100000010010100000100011 8
b00000011000000000000000011101111 9
b00000011000000000000000001101111 :
b00000000000010000000000011100111 ;
b00000000000010000000000001100111 <
b00001010000001000001000001100011 =
b00001010000001000000000001100011 >
b00000000100000000000100000010011 ?
b00001000000000000000100000110111 @
b00000000100010000001100000010011 A
b00000000000001000000000100110111 B
b00000110000000010001010000010011 C
b00000000100010000001100000010011 D
b00000000100001000101010000010011 E
b01000000100001000101010000010011 F
b00000000100010000000100000110011 G
b00000000100001000111010000010011 H
b00000000100000000000100000110011 I
b00000000100001000111010000110011 J
b00000000100001000110010000110011 K
b00000000100001000100010000110011 L
b01000000100001000000010000110011 M
b01000000100010010010100000100001 N
0O
b00000011000000000000000011101111 Q
#8
b000010000000 $
b000001000000 %
b000000000000 &
b000000000010 '
b00010 (
b00001 )
b00000000000001000010 *
b00000010000000000000 +
b00000000000010000000 ,
b010 -
b01001 .
b01010 /
b0100000010001001 0
b00000100 2
b000000000010 3
b000100000000 4
b00000000000001001010010100000011 5
b00000000101001001010000000100011 6
b00001000000000010010000010000011 7
b00000100001000010010000000100011 8
b00001000010000000000000011101111 9
b00001000010000000000000001101111 :
b00000000000000001000000011100111 ;
b00000000000000001000000001100111 <
b00000000000001001001001001100011 =
b00000000000001001000001001100011 >
b00000000001000000000000010010011 ?
b00000010000000000000000010110111 @
b00000000001000001010000010010011 A
b00000000000010000000000100110111 B
b00010000000000010010010100010011 C
b00000000001000001001000010010011 D
b00000000001001001101010010010011 E
b01000000001001001101010010010011 F
b00000000001000001000000010110011 G
b00000000001001001111010010010011 H
b00000000001000000000000010110011 I
b00000000101001001111010010110011 J
b00000000101001001110010010110011 K
b00000000101001001100010010110011 L
b01000000101001001000010010110011 M
1O
b00000000001000000000000010010011 Q
#9
b011 -
b0110000010001001 0
b00000000000001001011010100000011 5
b00001000000000010011000010000011 7
b00000000001000001011000010010011 A
b00010000000000010011010100010011 C
b10000000000010010110000010001001 N
0O
b00000010000000000000000010110111 Q
#10
b000000000000 %
b00000 )
b00000000000000000010 *
b100 -
b01000 .
b1000000000001001 0
b00000000 2
b000000000000 4
b00000000000001000100010100000011 5
b00000000101001000010000000100011 6
b00001000000000010100000000000011 7
b00000000001000010010000000100011 8
b00000000010000000000000011101111 9
b00000000010000000000000001101111 :
b00000000000000000000000011100111 ;
b00000000000000000000000001100111 <
b00000000000001000001001001100011 =
b00000000000001000000001001100011 >
b00000000001000000000000000010011 ?
b00000010000000000000000000110111 @
b00000000001000000100000000010011 A
b00000000000000010100010100010011 C
b00000000001000000001000000010011 D
b00000000001001000101010000010011 E
b01000000001001000101010000010011 F
b00000000001000000000000000110011 G
b00000000001001000111010000010011 H
b00000000001000000000000000110011 I
b00000000101001000111010000110011 J
b00000000101001000110010000110011 K
b00000000101001000100010000110011 L
b01000000101001000000010000110011 M
1O
b00000000001001000101010000010011 Q
#11
b000000001000 %
b000000001000 &
b01000 )
b00000000001000000010 *
b1000010000001001 0
b00100000 2
b000000001010 3
b100000000000 4
b00000000100001000100010100000011 5
b00000000101001000010010000100011 6
b00001000000000010100010000000011 7
b00000000001000010010010000100011 8
b01000000010000000000000011101111 9
b01000000010000000000000001101111 :
b00000000000001000000000011100111 ;
b00000000000001000000000001100111 <
b00000000000001000001101001100011 =
b00000000000001000000101001100011 >
b00000000001000000000010000010011 ?
b00000010000000000000010000110111 @
b00000000001001000100010000010011 A
b10000000000000010100010100010011 C
b00000000001001000001010000010011 D
b00000000001001000000010000110011 G
b00000000001000000000010000110011 I
b10001000000010011000010000001001 N
0O
b01000000001001000101010000010011 Q
#12
b000000010000 %
b000000010000 &
b10000 )
b00000000000000010010 *
b1000100000001001 0
b01000000 2
b000000010010 3
b000001000000 4
b00000001000001000100010100000011 5
b00000000101001000010100000100011 6
b00001000000000010100100000000011 7
b00000000001000010010100000100011 8
b00000010010000000000000011101111 9
b00000010010000000000000001101111 :
b00000000000010000000000011100111 ;
b00000000000010000000000001100111 <
b00000010000001000001001001100011 =
b00000010000001000000001001100011 >
b00000000001000000000100000010011 ?
b00000010000000000000100000110111 @
b00000000001010000100100000010011 A
b00000100000000010100010100010011 C
b00000000001010000001100000010011 D
b00000000001010000000100000110011 G
b00000000001000000000100000110011 I
1O
b00000000001001000111010000010011 Q
#13
b000001000000 $
b000000011000 %
b000000011000 &
b000000000001 '
b00001 (
b11000 )
b00000000001000110000 *
b00000001000000000000 +
b00000000000000100000 ,
b01001 /
b1000110000000101 0
b01100000 2
b000000111000 3
b100001000000 4
b00000001100001000100010010000011 5
b00000000100101000010110000100011 6
b00000100000000010100110000000011 7
b00000000000100010010110000100011 8
b01000110000000000000000011101111 9
b01000110000000000000000001101111 :
b00000000000011000000000011100111 ;
b00000000000011000000000001100111 <
b00000110000001000001100001100011 =
b00000110000001000000100001100011 >
b00000000000100000000110000010011 ?
b00000001000000000000110000110111 @
b00000000000111000100110000010011 A
b00000000000000100000000100110111 B
b10000100000000010100010010010011 C
b00000000000111000001110000010011 D
b00000000000101000101010000010011 E
b01000000000101000101010000010011 F
b00000000000111000000110000110011 G
b00000000000101000111010000010011 H
b00000000000100000000110000110011 I
b00000000100101000111010000110011 J
b00000000100101000110010000110011 K
b00000000100101000100010000110011 L
b01000000100101000000010000110011 M
b10001100010001011000110000000101 N
0O
b01000000100101000000010000110011 Q
#14
b000001010000 $
b000000011100 &
b000000010001 '
b10001 (
b00000000001010110000 *
b00010001000000000000 +
b00000000000000110000 ,
b1000110001000101 0
b01100010 2
b000010111000 3
b100001010000 4
b00000001110001000100010010000011 5
b00000000100101000010111000100011 6
b00000101000000010100110000000011 7
b00000001000100010010110000100011 8
b01010110000000000000000011101111 9
b01010110000000000000000001101111 :
b00010110000001000001100001100011 =
b00010110000001000000100001100011 >
b00000001000100000000110000010011 ?
b00010001000000000000110000110111 @
b00000001000111000100110000010011 A
b00000000000000110000000100110111 B
b10000101000000010100010010010011 C
b00000001000111000001110000010011 D
b00000001000101000101010000010011 E
b01000001000101000101010000010011 F
b00000001000111000000110000110011 G
b00000001000101000111010000010011 H
b00000001000100000000110000110011 I
1O
b00000000100101000110010000110011 Q
#15
b000001011000 $
b000001011100 &
b000000011001 '
b11001 (
b00000000001010111000 *
b00011001000000000000 +
b00000000000001110000 ,
b1000110001100101 0
b01100011 2
b000011111000 3
b100001110000 4
b00000101110001000100010010000011 5
b00000100100101000010111000100011 6
b00000101100000010100110000000011 7
b00000001100100010010110000100011 8
b01010111000000000000000011101111 9
b01010111000000000000000001101111 :
b00011110000001000001100001100011 =
b00011110000001000000100001100011 >
b00000001100100000000110000010011 ?
b00011001000000000000110000110111 @
b00000001100111000100110000010011 A
b00000000000001110000000100110111 B
b10000111000000010100010010010011 C
b00000001100111000001110000010011 D
b00000001100101000101010000010011 E
b01000001100101000101010000010011 F
b00000001100111000000110000110011 G
b00000001100101000111010000010011 H
b00000001100100000000110000110011 I
b10100000000110011000110001100101 N
0O
b00000000100101000111010000110011 Q
#16
b000010000100 $
b000000000000 %
b000000000000 &
b000000000110 '
b00110 (
b00000 )
b00000000000000000110 *
b00000110000000000000 +
b00000000000110000000 ,
b101 -
b01110 /
b1010000000011001 0
b00000000 2
b000000000110 3
b000000000000 4
b00000000000001000101011100000011 5
b00000000111001000010000000100011 6
b00001000010000010101000000000011 7
b00000000011000010010000000100011 8
b00000000110000000000000011101111 9
b00000000110000000000000001101111 :
b00000000000000000000000011100111 ;
b00000000000000000000000001100111 <
b00000000000001000001011001100011 =
b00000000000001000000011001100011 >
b00000000011000000000000000010011 ?
b00000110000000000000000000110111 @
b00000000011000000101000000010011 A
b00000000000110000000000100110111 B
b00000000000000010101011100010011 C
b00000000011000000001000000010011 D
b00000000011001000101010000010011 E
b01000000011001000101010000010011 F
b00000000011000000000000000110011 G
b00000000011001000111010000010011 H
b00000000011000000000000000110011 I
b00000000111001000111010000110011 J
b00000000111001000110010000110011 K
b00000000111001000100010000110011 L
b01000000111001000000010000110011 M
1O
b00000000110000000000000001101111 Q
